{
  "lastUpdated": "2025-12-13T18:31:07.248604+00:00",
  "articles": [
    {
      "title": "White Sox have reportedly shut down Red Sox\u2019 attempts to reacquire Kyle Teel",
      "link": "https://www.boston.com/sports/boston-red-sox/2025/12/13/red-sox-white-sox-kyle-teel-mlb-trade-rumors/",
      "pubDate": "Sat, 13 Dec 2025 18:00:36 +0000",
      "description": "<p>Teel was the headliner prospect the Red Sox gave up in the Garrett Crochet trade. </p>\n<p>The post <a href=\"https://www.boston.com/sports/boston-red-sox/2025/12/13/red-sox-white-sox-kyle-teel-mlb-trade-rumors/\">White Sox have reportedly shut down Red Sox&#8217; attempts to reacquire Kyle Teel</a> appeared first on <a href=\"https://www.boston.com\">Boston.com</a>.</p>",
      "id": "7a23f9780bd16838a24a3c6dffddcac7",
      "summary": [
        "Update: White Sox have reportedly shut down Red Sox\u2019 attem",
        "Details: <p>Teel was the headliner prospect the Red Sox gav",
        "Visit Boston.com for complete coverage"
      ],
      "hookType": "NEWS_UPDATE"
    },
    {
      "title": "5 things to know about the Bills before the Patriots play them on Sunday",
      "link": "https://www.boston.com/sports/new-england-patriots/2025/12/13/patriots-bills-nfl-week-15-preview/",
      "pubDate": "Sat, 13 Dec 2025 16:46:08 +0000",
      "description": "<p>The Bills have looked better as of late, even if Josh Allen has occasionally had to mask some of their flaws. </p>\n<p>The post <a href=\"https://www.boston.com/sports/new-england-patriots/2025/12/13/patriots-bills-nfl-week-15-preview/\">5 things to know about the Bills before the Patriots play them on Sunday</a> appeared first on <a href=\"https://www.boston.com\">Boston.com</a>.</p>",
      "id": "53de0570f03790eba806ee33be68ef6e",
      "summary": [
        "Update: 5 things to know about the Bills before the Patrio",
        "Details: <p>The Bills have looked better as of late, even i",
        "Visit Boston.com for complete coverage"
      ],
      "hookType": "NEWS_UPDATE"
    },
    {
      "title": "X marks spot where Will Flemming ran afoul of some mean-spirited Red Sox fans on social media",
      "link": "https://www.boston.com/sports/boston-red-sox/2025/12/13/red-sox-announcer-will-flemming-x-twitter/",
      "pubDate": "Sat, 13 Dec 2025 16:45:01 +0000",
      "description": "<p>For the third act of his X.com play after Red Sox fans took him to task when Pete Alonso signed with the Orioles, Flemming said he was done with the platform.</p>\n<p>The post <a href=\"https://www.boston.com/sports/boston-red-sox/2025/12/13/red-sox-announcer-will-flemming-x-twitter/\">X marks spot where Will Flemming ran afoul of some mean-spirited Red Sox fans on social media</a> appeared first on <a href=\"https://www.boston.com\">Boston.com</a>.</p>",
      "id": "caa5572755c86ec1afb2c484d72292ba",
      "summary": [
        "Update: X marks spot where Will Flemming ran afoul of some",
        "Details: <p>For the third act of his X.com play after Red S",
        "Visit Boston.com for complete coverage"
      ],
      "hookType": "NEWS_UPDATE"
    }
  ],
  "stats": {
    "totalProcessed": 3,
    "feedSize": 10,
    "timestamp": "2025-12-13T18:31:07.248627+00:00"
  }
}