{
  "lastUpdated": "2026-04-16T11:07:55.969570+00:00",
  "articles": [
    {
      "title": "Ask the remodeler: Is layered the new recessed lighting?",
      "link": "https://www.boston.com/real-estate/home-improvement/2026/04/16/layered-recessed-lighting-color-correlated-temperature/",
      "pubDate": "Thu, 16 Apr 2026 11:00:00 +0000",
      "description": "<p>Homeowners are looking for more out of their lighting these days, and a layered plan is in vogue. Here\u2019s what that means. </p>\n<p>The post <a href=\"https://www.boston.com/real-estate/home-improvement/2026/04/16/layered-recessed-lighting-color-correlated-temperature/\">Ask the remodeler: Is layered the new recessed lighting?</a> appeared first on <a href=\"https://www.boston.com\">Boston.com</a>.</p>",
      "id": "123f2305500a6d7fc679f4b326e2cf2c",
      "summary": [
        "Update: Ask the remodeler: Is layered the new recessed lig",
        "Details: <p>Homeowners are looking for more out of their li",
        "Visit Boston.com for complete coverage"
      ],
      "hookType": "NEWS_UPDATE"
    }
  ],
  "stats": {
    "totalProcessed": 1,
    "feedSize": 10,
    "timestamp": "2026-04-16T11:07:55.969591+00:00"
  }
}