{
  "lastUpdated": "2026-04-22T13:51:42.092182+00:00",
  "articles": [
    {
      "title": "Jeremy Swayman\u2019s greatest save in Game 2 had little to do with stopping pucks in Buffalo",
      "link": "https://www.boston.com/sports/boston-bruins/2026/04/22/boston-bruins-jeremy-swayman-nhl-hockey-game-2-buffalo-sabres-goalie-timeout/",
      "pubDate": "Wed, 22 Apr 2026 11:16:01 +0000",
      "description": "<p>\"A kid from Alaska never thought in a million years he\u2019d get his name chanted by 20,000.\"</p>\n<p>The post <a href=\"https://www.boston.com/sports/boston-bruins/2026/04/22/boston-bruins-jeremy-swayman-nhl-hockey-game-2-buffalo-sabres-goalie-timeout/\">Jeremy Swayman\u2019s greatest save in Game 2 had little to do with stopping pucks in Buffalo</a> appeared first on <a href=\"https://www.boston.com\">Boston.com</a>.</p>",
      "id": "3fde12455ed277f4678ac4a3ad39ccb3",
      "summary": [
        "Update: Jeremy Swayman\u2019s greatest save in Game 2 had littl",
        "Details: <p>\"A kid from Alaska never thought in a million y",
        "Visit Boston.com for complete coverage"
      ],
      "hookType": "NEWS_UPDATE"
    },
    {
      "title": "Recent homes sales in Greater Boston (April 22)",
      "link": "https://www.boston.com/real-estate/latest-sales/2026/04/22/recent-homes-sales-in-greater-boston-april-22/",
      "pubDate": "Wed, 22 Apr 2026 09:00:00 +0000",
      "description": "<p>ABINGTON 99 Washington St. One-family raised ranch, built in 2010, 1,871 square feet, 7 rooms, 3 bedrooms, 3 baths, on 33,958-square-foot lot. $681,000 332 Hancock St. One-family Colonial, built in 1900, 2,331 square feet, 9 rooms, 4 bedrooms, 2 baths, on 24,375-square-foot lot. $667,875 ACTON 27 Forest Road. One-family Colonial, built in 1966, 2,663 square [&#8230;]</p>\n<p>The post <a href=\"https://www.boston.com/real-estate/latest-sales/2026/04/22/recent-homes-sales-in-greater-boston-april-22/\">Recent homes sales in Greater Boston (April 22)</a> appeared first on <a href=\"https://www.boston.com\">Boston.com</a>.</p>",
      "id": "760fc1caa18a77b97c2075701affad58",
      "summary": [
        "Update: Recent homes sales in Greater Boston (April 22)",
        "Details: <p>ABINGTON 99 Washington St. One-family raised ra",
        "Visit Boston.com for complete coverage"
      ],
      "hookType": "NEWS_UPDATE"
    },
    {
      "title": "VJ Edgecombe, 76ers get hot, steal Game 2 against ice-cold Celtics: 7 takeaways",
      "link": "https://www.boston.com/sports/boston-celtics/2026/04/22/vj-edgecombe-76ers-get-hot-steal-game-2-against-ice-cold-celtics-7-takeaways/",
      "pubDate": "Wed, 22 Apr 2026 04:00:03 +0000",
      "description": "<p>Jaylen Brown mentioned Edgecombe by name three times unprompted as he explained what went wrong for the Celtics.</p>\n<p>The post <a href=\"https://www.boston.com/sports/boston-celtics/2026/04/22/vj-edgecombe-76ers-get-hot-steal-game-2-against-ice-cold-celtics-7-takeaways/\">VJ Edgecombe, 76ers get hot, steal Game 2 against ice-cold Celtics: 7 takeaways</a> appeared first on <a href=\"https://www.boston.com\">Boston.com</a>.</p>",
      "id": "068507d087bbb4f712eaaa0e8b813b42",
      "summary": [
        "Update: VJ Edgecombe, 76ers get hot, steal Game 2 against ",
        "Details: <p>Jaylen Brown mentioned Edgecombe by name three ",
        "Visit Boston.com for complete coverage"
      ],
      "hookType": "NEWS_UPDATE"
    },
    {
      "title": "Arvidsson scores 2 as Bruins beat Sabres 4-2 to even first-round series at 1",
      "link": "https://www.boston.com/sports/boston-bruins/2026/04/21/arvidsson-scores-2-as-bruins-beat-sabres-4-2-to-even-first-round-series-at-1/",
      "pubDate": "Wed, 22 Apr 2026 02:56:29 +0000",
      "description": "<p>Jeremy Swayman stopped 32 shots, and this time Boston managed to not blow a multigoal third-period lead.</p>\n<p>The post <a href=\"https://www.boston.com/sports/boston-bruins/2026/04/21/arvidsson-scores-2-as-bruins-beat-sabres-4-2-to-even-first-round-series-at-1/\">Arvidsson scores 2 as Bruins beat Sabres 4-2 to even first-round series at 1</a> appeared first on <a href=\"https://www.boston.com\">Boston.com</a>.</p>",
      "id": "2ae0a991d495b5ed96e7ab5f96844f3e",
      "summary": [
        "Update: Arvidsson scores 2 as Bruins beat Sabres 4-2 to ev",
        "Details: <p>Jeremy Swayman stopped 32 shots, and this time ",
        "Visit Boston.com for complete coverage"
      ],
      "hookType": "NEWS_UPDATE"
    },
    {
      "title": "24 hours after the 2026 Boston Marathon, the barefoot runner\u2019s feet are feeling \u2018great\u2019",
      "link": "https://www.boston.com/sports/local-news/2026/04/21/24-hours-after-the-2026-boston-marathon-the-barefoot-runners-feet-are-feeling-great/",
      "pubDate": "Wed, 22 Apr 2026 02:39:44 +0000",
      "description": "<p>\u201cThe only thing that hurts is, honestly, like my quads, my feet feel great though,\u201d Concannon said.</p>\n<p>The post <a href=\"https://www.boston.com/sports/local-news/2026/04/21/24-hours-after-the-2026-boston-marathon-the-barefoot-runners-feet-are-feeling-great/\">24 hours after the 2026 Boston Marathon, the barefoot runner\u2019s feet are feeling \u2018great\u2019</a> appeared first on <a href=\"https://www.boston.com\">Boston.com</a>.</p>",
      "id": "b6637662ea991eacb3e85a9f14b9f794",
      "summary": [
        "Update: 24 hours after the 2026 Boston Marathon, the baref",
        "Details: <p>\u201cThe only thing that hurts is, honestly, like m",
        "Visit Boston.com for complete coverage"
      ],
      "hookType": "NEWS_UPDATE"
    },
    {
      "title": "A Back Bay church says its \u2018God loves trans people\u2019 banner was stolen 3 times in a few weeks",
      "link": "https://www.boston.com/news/local-news/2026/04/21/a-back-bay-church-says-its-god-loves-trans-people-banner-was-stolen-three-times-in-a-few-weeks/",
      "pubDate": "Wed, 22 Apr 2026 02:20:36 +0000",
      "description": "<p>\u201cThis is something that we feel like it's important to be loud about, because certainly, the forces of hate are being pretty loud right now.\"</p>\n<p>The post <a href=\"https://www.boston.com/news/local-news/2026/04/21/a-back-bay-church-says-its-god-loves-trans-people-banner-was-stolen-three-times-in-a-few-weeks/\">A Back Bay church says its &#8216;God loves trans people&#8217; banner was stolen 3 times in a few weeks</a> appeared first on <a href=\"https://www.boston.com\">Boston.com</a>.</p>",
      "id": "052619fcc1d5c4c09b1e92d1b6025f0b",
      "summary": [
        "Update: A Back Bay church says its \u2018God loves trans people",
        "Details: <p>\u201cThis is something that we feel like it's impor",
        "Visit Boston.com for complete coverage"
      ],
      "hookType": "NEWS_UPDATE"
    },
    {
      "title": "Morgan Geekie scores bizarre Bruins goal after Ukko-Pekka Luukkonen lets in puck from center ice",
      "link": "https://www.boston.com/sports/boston-bruins/2026/04/21/boston-bruins-nhl-morgan-geekie-center-ice-goal-ukko-pekka-luukkonen/",
      "pubDate": "Wed, 22 Apr 2026 02:09:19 +0000",
      "description": "<p>The Bruins eventually chased Ukko-Pekka Luukkonen from Game 2 after allowing four goals on 19 shots. </p>\n<p>The post <a href=\"https://www.boston.com/sports/boston-bruins/2026/04/21/boston-bruins-nhl-morgan-geekie-center-ice-goal-ukko-pekka-luukkonen/\">Morgan Geekie scores bizarre Bruins goal after Ukko-Pekka Luukkonen lets in puck from center ice</a> appeared first on <a href=\"https://www.boston.com\">Boston.com</a>.</p>",
      "id": "5c40829e19d2415525ad276a3deba2a0",
      "summary": [
        "Update: Morgan Geekie scores bizarre Bruins goal after Ukk",
        "Details: <p>The Bruins eventually chased Ukko-Pekka Luukkon",
        "Visit Boston.com for complete coverage"
      ],
      "hookType": "NEWS_UPDATE"
    },
    {
      "title": "76ers beat Celtics 111-97 to tie first-round series at 1-1",
      "link": "https://www.boston.com/sports/boston-celtics/2026/04/21/76ers-beat-celtics-111-97-to-tie-first-round-series-at-1-1/",
      "pubDate": "Wed, 22 Apr 2026 02:01:27 +0000",
      "description": "<p>Jaylen Brown led the Celtics with 36 points. Jayson Tatum added 19 points, 14 rebounds and nine assists.</p>\n<p>The post <a href=\"https://www.boston.com/sports/boston-celtics/2026/04/21/76ers-beat-celtics-111-97-to-tie-first-round-series-at-1-1/\">76ers beat Celtics 111-97 to tie first-round series at 1-1</a> appeared first on <a href=\"https://www.boston.com\">Boston.com</a>.</p>",
      "id": "994282b7f47652c92a862160228303ba",
      "summary": [
        "Update: 76ers beat Celtics 111-97 to tie first-round serie",
        "Details: <p>Jaylen Brown led the Celtics with 36 points. Ja",
        "Visit Boston.com for complete coverage"
      ],
      "hookType": "NEWS_UPDATE"
    },
    {
      "title": "Red Sox shut out by Yankees 4-0 as Stanton homers, adds 2-run double",
      "link": "https://www.boston.com/sports/boston-red-sox/2026/04/21/red-sox-shut-out-by-yankees-4-0-as-stanton-homers-adds-2-run-double/",
      "pubDate": "Wed, 22 Apr 2026 01:56:13 +0000",
      "description": "<p>Boston lost for the third time in four games.</p>\n<p>The post <a href=\"https://www.boston.com/sports/boston-red-sox/2026/04/21/red-sox-shut-out-by-yankees-4-0-as-stanton-homers-adds-2-run-double/\">Red Sox shut out by Yankees 4-0 as Stanton homers, adds 2-run double</a> appeared first on <a href=\"https://www.boston.com\">Boston.com</a>.</p>",
      "id": "84cf904d90cbb8b612f17551cdd37c99",
      "summary": [
        "Update: Red Sox shut out by Yankees 4-0 as Stanton homers,",
        "Details: <p>Boston lost for the third time in four games.</",
        "Visit Boston.com for complete coverage"
      ],
      "hookType": "NEWS_UPDATE"
    },
    {
      "title": "Virginia voters approve redistricting plan that could boost Democrats\u2019 seats in Congress",
      "link": "https://www.boston.com/news/politics/2026/04/21/virginia-voters-approve-redistricting-plan-that-could-boost-democrats-seats-in-congress/",
      "pubDate": "Wed, 22 Apr 2026 01:16:18 +0000",
      "description": "<p>The constitutional amendment backed by voters bypasses a bipartisan redistricting commission to allow the use of\u00a0new districts\u00a0drawn by Virginia\u2019s Democratic-led General Assembly.</p>\n<p>The post <a href=\"https://www.boston.com/news/politics/2026/04/21/virginia-voters-approve-redistricting-plan-that-could-boost-democrats-seats-in-congress/\">Virginia voters approve redistricting plan that could boost Democrats\u2019 seats in Congress</a> appeared first on <a href=\"https://www.boston.com\">Boston.com</a>.</p>",
      "id": "38c5bc8d74d8bf6e5992565fc83c4c65",
      "summary": [
        "Update: Virginia voters approve redistricting plan that co",
        "Details: <p>The constitutional amendment backed by voters b",
        "Visit Boston.com for complete coverage"
      ],
      "hookType": "NEWS_UPDATE"
    },
    {
      "title": "\u2018This is our f\u2013ing city\u2019: Backlash ensues after DHS uses Fenway Park photo in social media post",
      "link": "https://www.boston.com/news/local-news/2026/04/21/this-is-our-f-ing-city-backlash-ensues-after-dhs-uses-fenway-park-photo-in-social-media-post/",
      "pubDate": "Wed, 22 Apr 2026 01:04:26 +0000",
      "description": "<p>\u201cThis is our f\u2013ing city, and nobody is going to dictate our freedom,\u201d Rep. Seth Moulton wrote.</p>\n<p>The post <a href=\"https://www.boston.com/news/local-news/2026/04/21/this-is-our-f-ing-city-backlash-ensues-after-dhs-uses-fenway-park-photo-in-social-media-post/\">\u2018This is our f\u2013ing city\u2019: Backlash ensues after DHS uses Fenway Park photo in social media post</a> appeared first on <a href=\"https://www.boston.com\">Boston.com</a>.</p>",
      "id": "8d9ada302c2b080c007e8ec93be740a1",
      "summary": [
        "Update: \u2018This is our f\u2013ing city\u2019: Backlash ensues after DH",
        "Details: <p>\u201cThis is our f\u2013ing city, and nobody is going to",
        "Visit Boston.com for complete coverage"
      ],
      "hookType": "NEWS_UPDATE"
    },
    {
      "title": "2 stabbed at hummus facility in Haverhill",
      "link": "https://www.boston.com/news/local-news/2026/04/21/2-stabbed-at-hummus-facility-in-haverhill/",
      "pubDate": "Wed, 22 Apr 2026 00:49:27 +0000",
      "description": "<p>Both people were brought to local hospitals with serious injuries, Haverhill police said.\u00a0</p>\n<p>The post <a href=\"https://www.boston.com/news/local-news/2026/04/21/2-stabbed-at-hummus-facility-in-haverhill/\">2 stabbed at hummus facility in Haverhill</a> appeared first on <a href=\"https://www.boston.com\">Boston.com</a>.</p>",
      "id": "dabc713d8843de6a251c5b7b70d191dd",
      "summary": [
        "Update: 2 stabbed at hummus facility in Haverhill",
        "Details: <p>Both people were brought to local hospitals wit",
        "Visit Boston.com for complete coverage"
      ],
      "hookType": "NEWS_UPDATE"
    },
    {
      "title": "Sixers need more from Tyrese Maxey to compete with Celtics",
      "link": "https://www.boston.com/sports/local-news/2026/04/21/sixers-need-more-from-tyrese-maxey-to-compete-with-celtics/",
      "pubDate": "Tue, 21 Apr 2026 23:51:36 +0000",
      "description": "<p>\u201cHe\u2019s got to be more aggressive and take more shots.\u201d</p>\n<p>The post <a href=\"https://www.boston.com/sports/local-news/2026/04/21/sixers-need-more-from-tyrese-maxey-to-compete-with-celtics/\">Sixers need more from Tyrese Maxey to compete with Celtics</a> appeared first on <a href=\"https://www.boston.com\">Boston.com</a>.</p>",
      "id": "71a27e559e80c3762478f5cff3ad4a9d",
      "summary": [
        "Update: Sixers need more from Tyrese Maxey to compete with",
        "Details: <p>\u201cHe\u2019s got to be more aggressive and take more s",
        "Visit Boston.com for complete coverage"
      ],
      "hookType": "NEWS_UPDATE"
    },
    {
      "title": "Woman charged in crash that killed Webster 10-year-old, allegedly was driving twice the speed limit",
      "link": "https://www.boston.com/news/local-news/2026/04/21/woman-charged-in-crash-that-killed-webster-10-year-old-allegedly-was-driving-twice-the-speed-limit/",
      "pubDate": "Tue, 21 Apr 2026 23:46:32 +0000",
      "description": "<p>Sherry Plitouke, 35, was caught on video less than a quarter-mile from the crash site going approximately 65 mph in a 30 mph speed limit zone, police wrote in court documents. </p>\n<p>The post <a href=\"https://www.boston.com/news/local-news/2026/04/21/woman-charged-in-crash-that-killed-webster-10-year-old-allegedly-was-driving-twice-the-speed-limit/\">Woman charged in crash that killed Webster 10-year-old, allegedly was driving twice the speed limit</a> appeared first on <a href=\"https://www.boston.com\">Boston.com</a>.</p>",
      "id": "6cdf34af715d76dd31f3198d6f9c92b6",
      "summary": [
        "Update: Woman charged in crash that killed Webster 10-year",
        "Details: <p>Sherry Plitouke, 35, was caught on video less t",
        "Visit Boston.com for complete coverage"
      ],
      "hookType": "NEWS_UPDATE"
    },
    {
      "title": "26-year-old identified as man killed by police in Lexington",
      "link": "https://www.boston.com/news/local-news/2026/04/21/26-year-old-identified-as-man-killed-by-police-in-lexington/",
      "pubDate": "Tue, 21 Apr 2026 22:33:45 +0000",
      "description": "<p>Police responded to a home in Lexington on Saturday after a resident reported that their son had injured himself with a knife, the DA said previously. </p>\n<p>The post <a href=\"https://www.boston.com/news/local-news/2026/04/21/26-year-old-identified-as-man-killed-by-police-in-lexington/\">26-year-old identified as man killed by police in Lexington</a> appeared first on <a href=\"https://www.boston.com\">Boston.com</a>.</p>",
      "id": "b6d91497b64110fd3b9db2d4dcfc8aaa",
      "summary": [
        "Update: 26-year-old identified as man killed by police in ",
        "Details: <p>Police responded to a home in Lexington on Satu",
        "Visit Boston.com for complete coverage"
      ],
      "hookType": "NEWS_UPDATE"
    },
    {
      "title": "\u200bAl Horford offers deeper explanation on cryptic comments about Celtics departure",
      "link": "https://www.boston.com/sports/boston-celtics/2026/04/21/al-horford-boston-celtics-warriors-exit-departure-free-agency-golden-state-nba-basketball/",
      "pubDate": "Tue, 21 Apr 2026 22:08:47 +0000",
      "description": "<p>\"I knew it was time for me to move on.\"</p>\n<p>The post <a href=\"https://www.boston.com/sports/boston-celtics/2026/04/21/al-horford-boston-celtics-warriors-exit-departure-free-agency-golden-state-nba-basketball/\">\u200bAl Horford offers deeper explanation on cryptic comments about Celtics departure</a> appeared first on <a href=\"https://www.boston.com\">Boston.com</a>.</p>",
      "id": "c512df0f7bd0e21fb1236e6d6142ae71",
      "summary": [
        "Update: \u200bAl Horford offers deeper explanation on cryptic c",
        "Details: <p>\"I knew it was time for me to move on.\"</p>\n<p>",
        "Visit Boston.com for complete coverage"
      ],
      "hookType": "NEWS_UPDATE"
    },
    {
      "title": "Trump says the US will extend its ceasefire with Iran at Pakistan\u2019s request",
      "link": "https://www.boston.com/news/politics/2026/04/21/trump-says-the-us-will-extend-its-ceasefire-with-iran-at-pakistans-request/",
      "pubDate": "Tue, 21 Apr 2026 20:41:42 +0000",
      "description": "<p>The announcement came as last-minute ceasefire talks between the US and Iran looked uncertain and a two-week truce was set to expire Wednesday.</p>\n<p>The post <a href=\"https://www.boston.com/news/politics/2026/04/21/trump-says-the-us-will-extend-its-ceasefire-with-iran-at-pakistans-request/\">Trump says the US will extend its ceasefire with Iran at Pakistan&#8217;s request</a> appeared first on <a href=\"https://www.boston.com\">Boston.com</a>.</p>",
      "id": "b1bf72898b86f202a21492523ecdedbd",
      "summary": [
        "Update: Trump says the US will extend its ceasefire with I",
        "Details: <p>The announcement came as last-minute ceasefire ",
        "Visit Boston.com for complete coverage"
      ],
      "hookType": "NEWS_UPDATE"
    },
    {
      "title": "\u2018Real Housewives of Rhode Island\u2019 Episode 4: Red pizza, rumors, and railroad rides",
      "link": "https://www.boston.com/culture/tv/2026/04/21/real-housewives-of-rhode-island-episode-4/",
      "pubDate": "Tue, 21 Apr 2026 20:30:47 +0000",
      "description": "<p>A breakout star, \u201cpizza chips,\u201d and beachside blowups \u2014 Episode 4 of The Real Housewives of Rhode Island finally delivers the drama.</p>\n<p>The post <a href=\"https://www.boston.com/culture/tv/2026/04/21/real-housewives-of-rhode-island-episode-4/\">&#8216;Real Housewives of Rhode Island&#8217; Episode 4: Red pizza, rumors, and railroad rides</a> appeared first on <a href=\"https://www.boston.com\">Boston.com</a>.</p>",
      "id": "6efe712febe6ae1213748f67fc48ccd6",
      "summary": [
        "Update: \u2018Real Housewives of Rhode Island\u2019 Episode 4: Red p",
        "Details: <p>A breakout star, \u201cpizza chips,\u201d and beachside b",
        "Visit Boston.com for complete coverage"
      ],
      "hookType": "NEWS_UPDATE"
    },
    {
      "title": "Democratic Rep. Sheila Cherfilus-McCormick of Florida resigns before the House can sanction her in ethics case",
      "link": "https://www.boston.com/news/politics/2026/04/21/democratic-rep-sheila-cherfilus-mccormick-of-florida-resigns-before-the-house-can-sanction-her-in-ethics-case/",
      "pubDate": "Tue, 21 Apr 2026 20:27:41 +0000",
      "description": "<p>The congresswoman was facing the possible threat of expulsion, something that has only occurred six times in the history of the House. </p>\n<p>The post <a href=\"https://www.boston.com/news/politics/2026/04/21/democratic-rep-sheila-cherfilus-mccormick-of-florida-resigns-before-the-house-can-sanction-her-in-ethics-case/\">Democratic Rep. Sheila Cherfilus-McCormick of Florida resigns before the House can sanction her in ethics case</a> appeared first on <a href=\"https://www.boston.com\">Boston.com</a>.</p>",
      "id": "1432c813591fe77cdab3e71186b15e31",
      "summary": [
        "Update: Democratic Rep. Sheila Cherfilus-McCormick of Flor",
        "Details: <p>The congresswoman was facing the possible threa",
        "Visit Boston.com for complete coverage"
      ],
      "hookType": "NEWS_UPDATE"
    },
    {
      "title": "Red Sox place righty Sonny Gray on injured list with hamstring strain, recall lefty Tyler Samaniego",
      "link": "https://www.boston.com/sports/boston-red-sox/2026/04/21/red-sox-place-righty-sonny-gray-on-injured-list-with-hamstring-strain-recall-lefty-tyler-samaniego/",
      "pubDate": "Tue, 21 Apr 2026 20:16:02 +0000",
      "description": "<p>\u201cI kind of knew what it was,\u201d Gray said. \u201cIt just happens every now and then.\"</p>\n<p>The post <a href=\"https://www.boston.com/sports/boston-red-sox/2026/04/21/red-sox-place-righty-sonny-gray-on-injured-list-with-hamstring-strain-recall-lefty-tyler-samaniego/\">Red Sox place righty Sonny Gray on injured list with hamstring strain, recall lefty Tyler Samaniego</a> appeared first on <a href=\"https://www.boston.com\">Boston.com</a>.</p>",
      "id": "62674ee56dc323110659b18ce30f315e",
      "summary": [
        "Update: Red Sox place righty Sonny Gray on injured list wi",
        "Details: <p>\u201cI kind of knew what it was,\u201d Gray said. \u201cIt ju",
        "Visit Boston.com for complete coverage"
      ],
      "hookType": "NEWS_UPDATE"
    },
    {
      "title": "Amtrak releases first look at new long distance fleet",
      "link": "https://www.boston.com/travel/new-england-travel/2026/04/21/amtrak-releases-first-look-at-new-long-distance-fleet/",
      "pubDate": "Tue, 21 Apr 2026 19:52:55 +0000",
      "description": "<p>The new rail cars will \"bring travelers the world-class service they deserve.\" </p>\n<p>The post <a href=\"https://www.boston.com/travel/new-england-travel/2026/04/21/amtrak-releases-first-look-at-new-long-distance-fleet/\">Amtrak releases first look at new long distance fleet</a> appeared first on <a href=\"https://www.boston.com\">Boston.com</a>.</p>",
      "id": "2680a61b0b0ec9f0023dca0551489f99",
      "summary": [
        "Update: Amtrak releases first look at new long distance fl",
        "Details: <p>The new rail cars will \"bring travelers the wor",
        "Visit Boston.com for complete coverage"
      ],
      "hookType": "NEWS_UPDATE"
    },
    {
      "title": "Clarke\u2019s, a 50-year-old bar at Faneuil Hall, has closed",
      "link": "https://www.boston.com/food/food-news/2026/04/21/clarkes-faneuil-hall-closed/",
      "pubDate": "Tue, 21 Apr 2026 19:41:36 +0000",
      "description": "<p>The owners told The Boston Globe that foot traffic downtown had not bounced back since the pandemic.</p>\n<p>The post <a href=\"https://www.boston.com/food/food-news/2026/04/21/clarkes-faneuil-hall-closed/\">Clarke&#8217;s, a 50-year-old bar at Faneuil Hall, has closed</a> appeared first on <a href=\"https://www.boston.com\">Boston.com</a>.</p>",
      "id": "8bd4d12c86adbb8a5c17680b8fe25808",
      "summary": [
        "Update: Clarke\u2019s, a 50-year-old bar at Faneuil Hall, has c",
        "Details: <p>The owners told The Boston Globe that foot traf",
        "Visit Boston.com for complete coverage"
      ],
      "hookType": "NEWS_UPDATE"
    },
    {
      "title": "With the Boston Marathon finish line in sight, they sacrificed personal goals to help a runner in need",
      "link": "https://www.boston.com/sports/boston-marathon/2026/04/21/with-the-boston-marathon-finish-line-in-sight-they-sacrificed-personal-goals-to-help-a-runner-in-need/",
      "pubDate": "Tue, 21 Apr 2026 19:31:02 +0000",
      "description": "<p>Israel Rivera and Henco Visser embodied the spirit of the 2026 Boston Marathon when they helped Jonathan Adams cross the finish line on Monday.</p>\n<p>The post <a href=\"https://www.boston.com/sports/boston-marathon/2026/04/21/with-the-boston-marathon-finish-line-in-sight-they-sacrificed-personal-goals-to-help-a-runner-in-need/\">With the Boston Marathon finish line in sight, they sacrificed personal goals to help a runner in need</a> appeared first on <a href=\"https://www.boston.com\">Boston.com</a>.</p>",
      "id": "314b01299dcf84f8c6cb2baa73d05278",
      "summary": [
        "Update: With the Boston Marathon finish line in sight, the",
        "Details: <p>Israel Rivera and Henco Visser embodied the spi",
        "Visit Boston.com for complete coverage"
      ],
      "hookType": "NEWS_UPDATE"
    },
    {
      "title": "What Boston meteorologists are saying about the \u2018rain and snow showers\u2019 in Wednesday\u2019s forecast",
      "link": "https://www.boston.com/weather/local-news/2026/04/21/boston-ma-rain-snow-forecast-wednesday/",
      "pubDate": "Tue, 21 Apr 2026 19:22:53 +0000",
      "description": "<p>\"Increasing clouds tonight with showers arriving from west to east early Wednesday morning.\"</p>\n<p>The post <a href=\"https://www.boston.com/weather/local-news/2026/04/21/boston-ma-rain-snow-forecast-wednesday/\">What Boston meteorologists are saying about the &#8216;rain and snow showers&#8217; in Wednesday&#8217;s forecast</a> appeared first on <a href=\"https://www.boston.com\">Boston.com</a>.</p>",
      "id": "d353d75c7cb3ae24b63ff6fec7c8c26b",
      "summary": [
        "Update: What Boston meteorologists are saying about the \u2018r",
        "Details: <p>\"Increasing clouds tonight with showers arrivin",
        "Visit Boston.com for complete coverage"
      ],
      "hookType": "NEWS_UPDATE"
    },
    {
      "title": "Former Brigham and Women\u2019s doctor indicted on 81 new sexual assault charges",
      "link": "https://www.boston.com/news/crime/2026/04/21/former-brigham-and-womens-doctor-indicted-on-81-new-sexual-assault-charges/",
      "pubDate": "Tue, 21 Apr 2026 18:37:29 +0000",
      "description": "<p>Dr. Derrick Todd is accused of performing unnecessary breast and pelvic exams on patients. He now faces more than 100 sexual assault charges in all.</p>\n<p>The post <a href=\"https://www.boston.com/news/crime/2026/04/21/former-brigham-and-womens-doctor-indicted-on-81-new-sexual-assault-charges/\">Former Brigham and Women\u2019s doctor indicted on 81 new sexual assault charges</a> appeared first on <a href=\"https://www.boston.com\">Boston.com</a>.</p>",
      "id": "d85d4f45a91920ce12af4a50e80ddd37",
      "summary": [
        "Update: Former Brigham and Women\u2019s doctor indicted on 81 n",
        "Details: <p>Dr. Derrick Todd is accused of performing unnec",
        "Visit Boston.com for complete coverage"
      ],
      "hookType": "NEWS_UPDATE"
    },
    {
      "title": "The \u2018Mother of the Boston Tea Party\u2019 honored with new Medford statue",
      "link": "https://www.boston.com/news/local-news/2026/04/21/the-mother-of-the-boston-tea-party-honored-with-new-medford-statue/",
      "pubDate": "Tue, 21 Apr 2026 17:39:45 +0000",
      "description": "<p>A long-overlooked American Revolutionary figure is recognized on Patriots' Day.</p>\n<p>The post <a href=\"https://www.boston.com/news/local-news/2026/04/21/the-mother-of-the-boston-tea-party-honored-with-new-medford-statue/\">The &#8216;Mother of the Boston Tea Party&#8217; honored with new Medford statue</a> appeared first on <a href=\"https://www.boston.com\">Boston.com</a>.</p>",
      "id": "8cd5cc35de1ffc591760262983fe6bec",
      "summary": [
        "Update: The \u2018Mother of the Boston Tea Party\u2019 honored with ",
        "Details: <p>A long-overlooked American Revolutionary figure",
        "Visit Boston.com for complete coverage"
      ],
      "hookType": "NEWS_UPDATE"
    },
    {
      "title": "Review and setlist: Florence + The Machine delivered a dark, intimate Boston show",
      "link": "https://www.boston.com/culture/concert-reviews/2026/04/21/review-and-setlist-florence-the-machine-at-td-garden-boston-4-20-26/",
      "pubDate": "Tue, 21 Apr 2026 17:38:20 +0000",
      "description": "<p>Florence + The Machine\u2019s rescheduled Boston stop traded arena spectacle for bare feet, huge vocals, and striking intimacy.</p>\n<p>The post <a href=\"https://www.boston.com/culture/concert-reviews/2026/04/21/review-and-setlist-florence-the-machine-at-td-garden-boston-4-20-26/\">Review and setlist: Florence + The Machine delivered a dark, intimate Boston show</a> appeared first on <a href=\"https://www.boston.com\">Boston.com</a>.</p>",
      "id": "27fcc0e8f303c19e6a3bf6f723d537b4",
      "summary": [
        "Update: Review and setlist: Florence + The Machine deliver",
        "Details: <p>Florence + The Machine\u2019s rescheduled Boston sto",
        "Visit Boston.com for complete coverage"
      ],
      "hookType": "NEWS_UPDATE"
    },
    {
      "title": "Mike Vrabel issues new statement on Dianna Russini photos, acknowledges \u2018difficult conversations\u2019",
      "link": "https://www.boston.com/sports/new-england-patriots/2026/04/21/mike-vrabel-dianna-russini-photos-scandal-new-england-patriots-nfl-football/",
      "pubDate": "Tue, 21 Apr 2026 17:20:57 +0000",
      "description": "<p>\"We believe in order to be successful on and off the field, we have to make good decisions. That includes me. That starts with me.\"</p>\n<p>The post <a href=\"https://www.boston.com/sports/new-england-patriots/2026/04/21/mike-vrabel-dianna-russini-photos-scandal-new-england-patriots-nfl-football/\">Mike Vrabel issues new statement on Dianna Russini photos, acknowledges \u2018difficult conversations\u2019</a> appeared first on <a href=\"https://www.boston.com\">Boston.com</a>.</p>",
      "id": "7e838d7cd87bcb0d7ddfd6d3db8fe1ca",
      "summary": [
        "Update: Mike Vrabel issues new statement on Dianna Russini",
        "Details: <p>\"We believe in order to be successful on and of",
        "Visit Boston.com for complete coverage"
      ],
      "hookType": "NEWS_UPDATE"
    },
    {
      "title": "Couple runs the Boston Marathon in wedding attire",
      "link": "https://www.boston.com/sports/boston-marathon/2026/04/21/couple-runs-the-boston-marathon-in-wedding-attire/",
      "pubDate": "Tue, 21 Apr 2026 17:00:29 +0000",
      "description": "<p>\u201cThe marathon has always been a very strong part of our relationship.\u201d</p>\n<p>The post <a href=\"https://www.boston.com/sports/boston-marathon/2026/04/21/couple-runs-the-boston-marathon-in-wedding-attire/\">Couple runs the Boston Marathon in wedding attire</a> appeared first on <a href=\"https://www.boston.com\">Boston.com</a>.</p>",
      "id": "691e573eeb9f2a9e0e67648d77632eca",
      "summary": [
        "Update: Couple runs the Boston Marathon in wedding attire",
        "Details: <p>\u201cThe marathon has always been a very strong par",
        "Visit Boston.com for complete coverage"
      ],
      "hookType": "NEWS_UPDATE"
    },
    {
      "title": "POST decertifies former Brandeis officer accused of negligence in student\u2019s 2023 death",
      "link": "https://www.boston.com/news/local-news/2026/04/21/post-decertifies-former-brandeis-officer-accused-of-negligence-in-students-2023-death/",
      "pubDate": "Tue, 21 Apr 2026 16:37:42 +0000",
      "description": "<p>Kimberly Carter is accused of mishandling a report of someone lying in the woods where sophomore Eli Stuart was ultimately found unresponsive hours later.</p>\n<p>The post <a href=\"https://www.boston.com/news/local-news/2026/04/21/post-decertifies-former-brandeis-officer-accused-of-negligence-in-students-2023-death/\">POST decertifies former Brandeis officer accused of negligence in student\u2019s 2023 death</a> appeared first on <a href=\"https://www.boston.com\">Boston.com</a>.</p>",
      "id": "503227080f4aaf6571f2ab840d7fe60c",
      "summary": [
        "Update: POST decertifies former Brandeis officer accused o",
        "Details: <p>Kimberly Carter is accused of mishandling a rep",
        "Visit Boston.com for complete coverage"
      ],
      "hookType": "NEWS_UPDATE"
    },
    {
      "title": "Epstein craved Harvard connections. Many there were eager to help.",
      "link": "https://www.boston.com/news/crime/2026/04/21/epstein-craved-harvard-connections-many-there-were-eager-to-help/",
      "pubDate": "Tue, 21 Apr 2026 16:26:16 +0000",
      "description": "<p>Newly released materials show how much Harvard professors did for Jeffrey Epstein, even after he became a convicted sex offender.</p>\n<p>The post <a href=\"https://www.boston.com/news/crime/2026/04/21/epstein-craved-harvard-connections-many-there-were-eager-to-help/\">Epstein craved Harvard connections. Many there were eager to help.</a> appeared first on <a href=\"https://www.boston.com\">Boston.com</a>.</p>",
      "id": "73876d65085efb89e6660e005470230d",
      "summary": [
        "Update: Epstein craved Harvard connections. Many there wer",
        "Details: <p>Newly released materials show how much Harvard ",
        "Visit Boston.com for complete coverage"
      ],
      "hookType": "NEWS_UPDATE"
    },
    {
      "title": "Watch: Noah Kahan makes his NPR Tiny Desk debut ahead of new album release",
      "link": "https://www.boston.com/culture/music/2026/04/21/noah-kahan-npr-tiny-desk-concert/",
      "pubDate": "Tue, 21 Apr 2026 15:49:31 +0000",
      "description": "<p>A look at the singer-songwriter's X (Twitter) history reveals years of manifesting this very moment. </p>\n<p>The post <a href=\"https://www.boston.com/culture/music/2026/04/21/noah-kahan-npr-tiny-desk-concert/\">Watch: Noah Kahan makes his NPR Tiny Desk debut ahead of new album release</a> appeared first on <a href=\"https://www.boston.com\">Boston.com</a>.</p>",
      "id": "4b9df526ae0b293357d058cbdd0dba9c",
      "summary": [
        "Update: Watch: Noah Kahan makes his NPR Tiny Desk debut ah",
        "Details: <p>A look at the singer-songwriter's X (Twitter) h",
        "Visit Boston.com for complete coverage"
      ],
      "hookType": "NEWS_UPDATE"
    },
    {
      "title": "Quincy resident plans to buy a house and car after $4M scratch ticket win",
      "link": "https://www.boston.com/news/local-news/2026/04/21/quincy-resident-plans-to-buy-a-house-and-car-after-4m-scratch-ticket-win/",
      "pubDate": "Tue, 21 Apr 2026 15:40:22 +0000",
      "description": "<p>The ticket was purchased at Richdale Food Shops in Rockland.</p>\n<p>The post <a href=\"https://www.boston.com/news/local-news/2026/04/21/quincy-resident-plans-to-buy-a-house-and-car-after-4m-scratch-ticket-win/\">Quincy resident plans to buy a house and car after $4M scratch ticket win</a> appeared first on <a href=\"https://www.boston.com\">Boston.com</a>.</p>",
      "id": "1d3cf4c4f5098e28be9cad8f02596b39",
      "summary": [
        "Update: Quincy resident plans to buy a house and car after",
        "Details: <p>The ticket was purchased at Richdale Food Shops",
        "Visit Boston.com for complete coverage"
      ],
      "hookType": "NEWS_UPDATE"
    },
    {
      "title": "A significant Green Line shutdown starts Wednesday",
      "link": "https://www.boston.com/news/local-news/2026/04/21/a-significant-green-line-shutdown-starts-wednesday/",
      "pubDate": "Tue, 21 Apr 2026 15:25:23 +0000",
      "description": "<p>An MBTA suspension between Kenmore and Boston College will bring shuttle buses and reduced service through April 30.</p>\n<p>The post <a href=\"https://www.boston.com/news/local-news/2026/04/21/a-significant-green-line-shutdown-starts-wednesday/\">A significant Green Line shutdown starts Wednesday</a> appeared first on <a href=\"https://www.boston.com\">Boston.com</a>.</p>",
      "id": "0ee324715a6759977d55a366f7c7339b",
      "summary": [
        "Update: A significant Green Line shutdown starts Wednesday",
        "Details: <p>An MBTA suspension between Kenmore and Boston C",
        "Visit Boston.com for complete coverage"
      ],
      "hookType": "NEWS_UPDATE"
    },
    {
      "title": "Here\u2019s the \u2018ascending prospect\u2019 the Patriots are projected to take in the NFL Draft",
      "link": "https://www.boston.com/sports/morning-sports-update/2026/04/21/patriots-mock-draft-max-iheanachor/",
      "pubDate": "Tue, 21 Apr 2026 14:53:33 +0000",
      "description": "<p>\"Iheanachor is a mauler with the size, strength and athleticism to flourish as a heavy-handed right tackle.\"</p>\n<p>The post <a href=\"https://www.boston.com/sports/morning-sports-update/2026/04/21/patriots-mock-draft-max-iheanachor/\">Here&#8217;s the &#8216;ascending prospect&#8217; the Patriots are projected to take in the NFL Draft</a> appeared first on <a href=\"https://www.boston.com\">Boston.com</a>.</p>",
      "id": "f63d823e8ed2fd885ba93a2f57f5c62e",
      "summary": [
        "Update: Here\u2019s the \u2018ascending prospect\u2019 the Patriots are p",
        "Details: <p>\"Iheanachor is a mauler with the size, strength",
        "Visit Boston.com for complete coverage"
      ],
      "hookType": "NEWS_UPDATE"
    },
    {
      "title": "Local obituary: Michael Flynn, 47, Norwood father of 3 and hockey coach",
      "link": "https://www.boston.com/news/massachusetts-obituaries/2026/04/21/local-obituary-michael-flynn-47-norwood-father-of-3-and-hockey-coach/",
      "pubDate": "Tue, 21 Apr 2026 14:31:46 +0000",
      "description": "<p>\"Whether on or off the ice, he was more than a coach, he was a mentor and role model.\"</p>\n<p>The post <a href=\"https://www.boston.com/news/massachusetts-obituaries/2026/04/21/local-obituary-michael-flynn-47-norwood-father-of-3-and-hockey-coach/\">Local obituary: Michael Flynn, 47, Norwood father of 3 and hockey coach</a> appeared first on <a href=\"https://www.boston.com\">Boston.com</a>.</p>",
      "id": "8869adc46eea6f2b49845c1d9d31b6c2",
      "summary": [
        "Update: Local obituary: Michael Flynn, 47, Norwood father ",
        "Details: <p>\"Whether on or off the ice, he was more than a ",
        "Visit Boston.com for complete coverage"
      ],
      "hookType": "NEWS_UPDATE"
    },
    {
      "title": "Mass. teens rescued from near the top of Mount Washington",
      "link": "https://www.boston.com/news/local-news/2026/04/21/mass-teens-rescued-from-near-the-top-of-mount-washington/",
      "pubDate": "Tue, 21 Apr 2026 14:08:48 +0000",
      "description": "<p>One of the teens reported experiencing leg pain, as crews raced worsening weather to reach them.</p>\n<p>The post <a href=\"https://www.boston.com/news/local-news/2026/04/21/mass-teens-rescued-from-near-the-top-of-mount-washington/\">Mass. teens rescued from near the top of Mount Washington</a> appeared first on <a href=\"https://www.boston.com\">Boston.com</a>.</p>",
      "id": "18b69e928dcf77e72dd82b39427ae26d",
      "summary": [
        "Update: Mass. teens rescued from near the top of Mount Was",
        "Details: <p>One of the teens reported experiencing leg pain",
        "Visit Boston.com for complete coverage"
      ],
      "hookType": "NEWS_UPDATE"
    },
    {
      "title": "Man killed, officer shot during traffic stop in New Hampshire",
      "link": "https://www.boston.com/news/local-news/2026/04/21/man-killed-officer-shot-during-traffic-stop-in-new-hampshire/",
      "pubDate": "Tue, 21 Apr 2026 13:59:19 +0000",
      "description": "<p>The deadly officer-involved shooting occurred Monday evening in Ashland, New Hampshire.</p>\n<p>The post <a href=\"https://www.boston.com/news/local-news/2026/04/21/man-killed-officer-shot-during-traffic-stop-in-new-hampshire/\">Man killed, officer shot during traffic stop in New Hampshire</a> appeared first on <a href=\"https://www.boston.com\">Boston.com</a>.</p>",
      "id": "1e362772a238cc3f196868795d8a088b",
      "summary": [
        "Update: Man killed, officer shot during traffic stop in Ne",
        "Details: <p>The deadly officer-involved shooting occurred M",
        "Visit Boston.com for complete coverage"
      ],
      "hookType": "NEWS_UPDATE"
    },
    {
      "title": "Repeat winners Sharon Lokedi, John Korir proved Boston Marathon favorites in more ways than one",
      "link": "https://www.boston.com/sports/boston-marathon/2026/04/21/sharon-lokedi-john-korir-boston-marathon-favorites/",
      "pubDate": "Tue, 21 Apr 2026 11:50:58 +0000",
      "description": "<p>Upon hearing his news, she clapped her hands, patted her countryman on the shoulders, and said, \u201cGood job! Good job!\u201d</p>\n<p>The post <a href=\"https://www.boston.com/sports/boston-marathon/2026/04/21/sharon-lokedi-john-korir-boston-marathon-favorites/\">Repeat winners Sharon Lokedi, John Korir proved Boston Marathon favorites in more ways than one</a> appeared first on <a href=\"https://www.boston.com\">Boston.com</a>.</p>",
      "id": "ae1e2fae43f0eefc7677ef4ead9f36d3",
      "summary": [
        "Update: Repeat winners Sharon Lokedi, John Korir proved Bo",
        "Details: <p>Upon hearing his news, she clapped her hands, p",
        "Visit Boston.com for complete coverage"
      ],
      "hookType": "NEWS_UPDATE"
    },
    {
      "title": "Home of the Week: 3BR in Sherborn offers open space in MetroWest for $799k",
      "link": "https://www.boston.com/real-estate/home-of-the-week/2026/04/21/sherborn-metrowest-colonial-for-sale/",
      "pubDate": "Tue, 21 Apr 2026 11:00:00 +0000",
      "description": "<p>Sherborn is a proudly bucolic town about 25 miles from downtown Boston that boasts 50 percent of its land is set aside for open space.</p>\n<p>The post <a href=\"https://www.boston.com/real-estate/home-of-the-week/2026/04/21/sherborn-metrowest-colonial-for-sale/\">Home of the Week: 3BR in Sherborn offers open space in MetroWest for $799k</a> appeared first on <a href=\"https://www.boston.com\">Boston.com</a>.</p>",
      "id": "0004e3be26cb1a8501ea4c1681a53904",
      "summary": [
        "Update: Home of the Week: 3BR in Sherborn offers open spac",
        "Details: <p>Sherborn is a proudly bucolic town about 25 mil",
        "Visit Boston.com for complete coverage"
      ],
      "hookType": "NEWS_UPDATE"
    },
    {
      "title": "Patriots WR Kayshon Boutte reportedly mentioned in trade talks this offseason",
      "link": "https://www.boston.com/sports/new-england-patriots/2026/04/20/kayshon-boutte-trade-rumors-nfl-football-new-england-patriots/",
      "pubDate": "Tue, 21 Apr 2026 01:57:26 +0000",
      "description": "<p>\"With Romeo Doubs coming in and the eventual AJ Brown trade, teams believe he could be available for the right price.\"</p>\n<p>The post <a href=\"https://www.boston.com/sports/new-england-patriots/2026/04/20/kayshon-boutte-trade-rumors-nfl-football-new-england-patriots/\">Patriots WR Kayshon Boutte reportedly mentioned in trade talks this offseason</a> appeared first on <a href=\"https://www.boston.com\">Boston.com</a>.</p>",
      "id": "c029ea46c0e12a4577f74e0b36509f42",
      "summary": [
        "Update: Patriots WR Kayshon Boutte reportedly mentioned in",
        "Details: <p>\"With Romeo Doubs coming in and the eventual AJ",
        "Visit Boston.com for complete coverage"
      ],
      "hookType": "NEWS_UPDATE"
    },
    {
      "title": "Martin Richard\u2019s brother finishes his 3rd Boston Marathon",
      "link": "https://www.boston.com/sports/boston-marathon/2026/04/20/brother-of-martin-richard-finishes-third-boston-marathon/",
      "pubDate": "Tue, 21 Apr 2026 01:19:27 +0000",
      "description": "<p>\"He's in my mind every day, especially on a meaningful day like today,\" Henry Richard said at the Boston Marathon finish line on Monday.</p>\n<p>The post <a href=\"https://www.boston.com/sports/boston-marathon/2026/04/20/brother-of-martin-richard-finishes-third-boston-marathon/\">Martin Richard&#8217;s brother finishes his 3rd Boston Marathon</a> appeared first on <a href=\"https://www.boston.com\">Boston.com</a>.</p>",
      "id": "7938c0a49180d4905c77d14144a439eb",
      "summary": [
        "Update: Martin Richard\u2019s brother finishes his 3rd Boston M",
        "Details: <p>\"He's in my mind every day, especially on a mea",
        "Visit Boston.com for complete coverage"
      ],
      "hookType": "NEWS_UPDATE"
    },
    {
      "title": "At Rochambeau, Boston Marathon runners met with applause and cowbells",
      "link": "https://www.boston.com/sports/boston-marathon/2026/04/20/boston-marathon-runners-rochambeau/",
      "pubDate": "Tue, 21 Apr 2026 00:39:31 +0000",
      "description": "<p>Cheering on runners isn't just for the course. At restaurants around Boston, runners get ovations when they walk in. </p>\n<p>The post <a href=\"https://www.boston.com/sports/boston-marathon/2026/04/20/boston-marathon-runners-rochambeau/\">At Rochambeau, Boston Marathon runners met with applause and cowbells</a> appeared first on <a href=\"https://www.boston.com\">Boston.com</a>.</p>",
      "id": "75bcca58aeae219b035f5d0124119e0b",
      "summary": [
        "Update: At Rochambeau, Boston Marathon runners met with ap",
        "Details: <p>Cheering on runners isn't just for the course. ",
        "Visit Boston.com for complete coverage"
      ],
      "hookType": "NEWS_UPDATE"
    },
    {
      "title": "James Hagens and Bruins\u2019 \u2018kid line\u2019 received a seal of approval after playoff debut",
      "link": "https://www.boston.com/sports/boston-bruins/2026/04/20/boston-bruins-james-hagens-playoffs-nhl-fraser-minten-nhl-hockey-rookies/",
      "pubDate": "Tue, 21 Apr 2026 00:33:24 +0000",
      "description": "<p>\"They were our best defensive line yesterday, I thought.\"</p>\n<p>The post <a href=\"https://www.boston.com/sports/boston-bruins/2026/04/20/boston-bruins-james-hagens-playoffs-nhl-fraser-minten-nhl-hockey-rookies/\">James Hagens and Bruins\u2019 \u2018kid line\u2019 received a seal of approval after playoff debut</a> appeared first on <a href=\"https://www.boston.com\">Boston.com</a>.</p>",
      "id": "def8b627616f96f94e3449207c7845fc",
      "summary": [
        "Update: James Hagens and Bruins\u2019 \u2018kid line\u2019 received a sea",
        "Details: <p>\"They were our best defensive line yesterday, I",
        "Visit Boston.com for complete coverage"
      ],
      "hookType": "NEWS_UPDATE"
    },
    {
      "title": "After the Boston Marathon, the clam chowder ritual begins",
      "link": "https://www.boston.com/sports/boston-marathon/2026/04/20/after-the-boston-marathon-the-clam-chowder-ritual-begins/",
      "pubDate": "Tue, 21 Apr 2026 00:15:54 +0000",
      "description": "<p>\u201cI ate that chowder in record speed ... Two personal records in one day!\u201d</p>\n<p>The post <a href=\"https://www.boston.com/sports/boston-marathon/2026/04/20/after-the-boston-marathon-the-clam-chowder-ritual-begins/\">After the Boston Marathon, the clam chowder ritual begins</a> appeared first on <a href=\"https://www.boston.com\">Boston.com</a>.</p>",
      "id": "4cb7933e6ade9f43450342801d847812",
      "summary": [
        "Update: After the Boston Marathon, the clam chowder ritual",
        "Details: <p>\u201cI ate that chowder in record speed ... Two per",
        "Visit Boston.com for complete coverage"
      ],
      "hookType": "NEWS_UPDATE"
    },
    {
      "title": "Photos: The best costumes from the 2026 Boston Marathon",
      "link": "https://www.boston.com/sports/boston-marathon/2026/04/20/photos-the-best-costumes-from-the-2026-boston-marathon/",
      "pubDate": "Mon, 20 Apr 2026 23:34:33 +0000",
      "description": "<p>Here are just some of the outrageous, surprising, cute, and funny costumes that graced the Boston Marathon course Monday.</p>\n<p>The post <a href=\"https://www.boston.com/sports/boston-marathon/2026/04/20/photos-the-best-costumes-from-the-2026-boston-marathon/\">Photos: The best costumes from the 2026 Boston Marathon</a> appeared first on <a href=\"https://www.boston.com\">Boston.com</a>.</p>",
      "id": "ada997b945ca27ebad66c383ff1f3aa1",
      "summary": [
        "Update: Photos: The best costumes from the 2026 Boston Mar",
        "Details: <p>Here are just some of the outrageous, surprisin",
        "Visit Boston.com for complete coverage"
      ],
      "hookType": "NEWS_UPDATE"
    },
    {
      "title": "After the Marathon, this Boston running group meets in the basement at Clery\u2019s",
      "link": "https://www.boston.com/sports/boston-marathon/2026/04/20/boston-marathon-clerys-tradition/",
      "pubDate": "Mon, 20 Apr 2026 23:30:39 +0000",
      "description": "<p>\"It\u2019s common when we pass each other on the course to say, \u2018See you at Clery\u2019s.\u2019\u201d</p>\n<p>The post <a href=\"https://www.boston.com/sports/boston-marathon/2026/04/20/boston-marathon-clerys-tradition/\">After the Marathon, this Boston running group meets in the basement at Clery&#8217;s</a> appeared first on <a href=\"https://www.boston.com\">Boston.com</a>.</p>",
      "id": "c60c27135fbf01a1b1bdfc371e293d58",
      "summary": [
        "Update: After the Marathon, this Boston running group meet",
        "Details: <p>\"It\u2019s common when we pass each other on the cou",
        "Visit Boston.com for complete coverage"
      ],
      "hookType": "NEWS_UPDATE"
    },
    {
      "title": "This 2026 Boston Marathon finisher ran the whole race barefoot",
      "link": "https://www.boston.com/sports/boston-marathon/2026/04/20/this-2026-boston-marathon-finisher-ran-the-whole-race-barefoot/",
      "pubDate": "Mon, 20 Apr 2026 23:23:15 +0000",
      "description": "<p>Terrence Concannon, a former Mass. resident, ran 26.2 miles at the 2026 Boston Marathon barefoot.</p>\n<p>The post <a href=\"https://www.boston.com/sports/boston-marathon/2026/04/20/this-2026-boston-marathon-finisher-ran-the-whole-race-barefoot/\">This 2026 Boston Marathon finisher ran the whole race barefoot</a> appeared first on <a href=\"https://www.boston.com\">Boston.com</a>.</p>",
      "id": "32af1a989e0642f42b484049f4d3d5d9",
      "summary": [
        "Update: This 2026 Boston Marathon finisher ran the whole r",
        "Details: <p>Terrence Concannon, a former Mass. resident, ra",
        "Visit Boston.com for complete coverage"
      ],
      "hookType": "NEWS_UPDATE"
    },
    {
      "title": "It wasn\u2019t pretty, but the Red Sox bats finally woke up on Patriots\u2019 Day",
      "link": "https://www.boston.com/sports/boston-red-sox/2026/04/20/boston-red-sox-lineup-bats-offense-marathon-monday-patriots-day/",
      "pubDate": "Mon, 20 Apr 2026 22:41:07 +0000",
      "description": "<p>\u201cI\u2019m not saying this is the brand of baseball we\u2019re gonna have to play over 162 to get going, but it\u2019s a cool way to do it.\"</p>\n<p>The post <a href=\"https://www.boston.com/sports/boston-red-sox/2026/04/20/boston-red-sox-lineup-bats-offense-marathon-monday-patriots-day/\">It wasn\u2019t pretty, but the Red Sox bats finally woke up on Patriots&#8217; Day</a> appeared first on <a href=\"https://www.boston.com\">Boston.com</a>.</p>",
      "id": "c7c2dd9177c939f609cd0f0668a70fc2",
      "summary": [
        "Update: It wasn\u2019t pretty, but the Red Sox bats finally wok",
        "Details: <p>\u201cI\u2019m not saying this is the brand of baseball w",
        "Visit Boston.com for complete coverage"
      ],
      "hookType": "NEWS_UPDATE"
    },
    {
      "title": "Joel Embiid enters new phase of recovery process, but will miss Game 2 against Celtics",
      "link": "https://www.boston.com/sports/boston-celtics/2026/04/20/celtics-sixers-joel-embiid-injury-status-game-2-playoffs/",
      "pubDate": "Mon, 20 Apr 2026 22:11:03 +0000",
      "description": "<p>Embiid has begun the strength and conditioning part of his process, but will not play Tuesday night at TD Garden. </p>\n<p>The post <a href=\"https://www.boston.com/sports/boston-celtics/2026/04/20/celtics-sixers-joel-embiid-injury-status-game-2-playoffs/\">Joel Embiid enters new phase of recovery process, but will miss Game 2 against Celtics</a> appeared first on <a href=\"https://www.boston.com\">Boston.com</a>.</p>",
      "id": "0442bbd523ca9fcda4af966766ad49ac",
      "summary": [
        "Update: Joel Embiid enters new phase of recovery process, ",
        "Details: <p>Embiid has begun the strength and conditioning ",
        "Visit Boston.com for complete coverage"
      ],
      "hookType": "NEWS_UPDATE"
    }
  ],
  "totalArticles": 50
}