{
  "lastUpdated": "2026-01-11T04:50:28.426826+00:00",
  "articles": [
    {
      "title": "Red Sox lose Alex Bregman to Cubs, who reportedly sign him to $175 million deal",
      "link": "https://www.boston.com/sports/boston-red-sox/2026/01/10/alex-bregman-cubs-red-sox-mlb-free-agency/",
      "pubDate": "Sun, 11 Jan 2026 04:16:00 +0000",
      "description": "<p>The Red Sox were hoping to bring Bregman back to Boston, but lost out to Chicago.</p>\n<p>The post <a href=\"https://www.boston.com/sports/boston-red-sox/2026/01/10/alex-bregman-cubs-red-sox-mlb-free-agency/\">Red Sox lose Alex Bregman to Cubs, who reportedly sign him to $175 million deal</a> appeared first on <a href=\"https://www.boston.com\">Boston.com</a>.</p>",
      "id": "a012544be02c159e5be78226444bb991",
      "summary": [
        "Update: Red Sox lose Alex Bregman to Cubs, who reportedly ",
        "Details: <p>The Red Sox were hoping to bring Bregman back t",
        "Visit Boston.com for complete coverage"
      ],
      "hookType": "NEWS_UPDATE"
    }
  ],
  "stats": {
    "totalProcessed": 1,
    "feedSize": 10,
    "timestamp": "2026-01-11T04:50:28.426846+00:00"
  }
}