{
  "lastUpdated": "2026-05-08T15:45:10.511750+00:00",
  "articles": [
    {
      "title": "New Emerson poll suggests Moulton is gaining ground on Markey",
      "link": "https://www.boston.com/news/local-news/2026/05/08/new-emerson-poll-suggests-moulton-is-gaining-ground-on-markey/",
      "pubDate": "Fri, 08 May 2026 15:09:34 +0000",
      "description": "<p>Incumbent Sen. Ed Markey is still leading his younger challenger, Rep. Seth Moulton, but the gap appears to be shrinking. </p>\n<p>The post <a href=\"https://www.boston.com/news/local-news/2026/05/08/new-emerson-poll-suggests-moulton-is-gaining-ground-on-markey/\">New Emerson poll suggests Moulton is gaining ground on Markey</a> appeared first on <a href=\"https://www.boston.com\">Boston.com</a>.</p>",
      "id": "f6dee132afa2712baba6bb740e49a29a",
      "summary": [
        "Update: New Emerson poll suggests Moulton is gaining groun",
        "Details: <p>Incumbent Sen. Ed Markey is still leading his y",
        "Visit Boston.com for complete coverage"
      ],
      "hookType": "NEWS_UPDATE"
    },
    {
      "title": "This is the best Cape Cod town, according to Boston.com readers",
      "link": "https://www.boston.com/community/readers-say/2026/05/08/the-best-cape-cod-town/",
      "pubDate": "Fri, 08 May 2026 14:55:00 +0000",
      "description": "<p>\"Small-town feeling, nice place to walk around, beautiful beaches.\"</p>\n<p>The post <a href=\"https://www.boston.com/community/readers-say/2026/05/08/the-best-cape-cod-town/\">This is the best Cape Cod town, according to Boston.com readers</a> appeared first on <a href=\"https://www.boston.com\">Boston.com</a>.</p>",
      "id": "4dcd26c487196f882b7a0cbec447189f",
      "summary": [
        "Update: This is the best Cape Cod town, according to Bosto",
        "Details: <p>\"Small-town feeling, nice place to walk around,",
        "Visit Boston.com for complete coverage"
      ],
      "hookType": "NEWS_UPDATE"
    },
    {
      "title": "Teen arrested for stabbing death of Worcester man in Times Square",
      "link": "https://www.boston.com/news/crime/2026/05/08/teen-arrested-for-stabbing-death-of-worcester-man-in-times-square/",
      "pubDate": "Fri, 08 May 2026 14:53:28 +0000",
      "description": "<p>The 17-year-old is accused of two other stabbings, including one on this past Sunday, court documents show. </p>\n<p>The post <a href=\"https://www.boston.com/news/crime/2026/05/08/teen-arrested-for-stabbing-death-of-worcester-man-in-times-square/\">Teen arrested for stabbing death of Worcester man in Times Square</a> appeared first on <a href=\"https://www.boston.com\">Boston.com</a>.</p>",
      "id": "c97ff99d57230ecbcacf60c04d60de33",
      "summary": [
        "Update: Teen arrested for stabbing death of Worcester man ",
        "Details: <p>The 17-year-old is accused of two other stabbin",
        "Visit Boston.com for complete coverage"
      ],
      "hookType": "NEWS_UPDATE"
    },
    {
      "title": "Red Sox pitcher offers candid quote after latest setback",
      "link": "https://www.boston.com/sports/morning-sports-update/2026/05/08/red-sox-pitcher-offers-candid-quote-after-latest-setback/",
      "pubDate": "Fri, 08 May 2026 14:47:28 +0000",
      "description": "<p>\"I come in and blow it. It sucks.\"</p>\n<p>The post <a href=\"https://www.boston.com/sports/morning-sports-update/2026/05/08/red-sox-pitcher-offers-candid-quote-after-latest-setback/\">Red Sox pitcher offers candid quote after latest setback</a> appeared first on <a href=\"https://www.boston.com\">Boston.com</a>.</p>",
      "id": "910f17ebee5402e0217ef22ba0dae522",
      "summary": [
        "Update: Red Sox pitcher offers candid quote after latest s",
        "Details: <p>\"I come in and blow it. It sucks.\"</p>\n<p>The p",
        "Visit Boston.com for complete coverage"
      ],
      "hookType": "NEWS_UPDATE"
    },
    {
      "title": "If this was Jaylen Brown\u2019s \u2018favorite\u2019 Celtics season, maybe it\u2019s time to let him leave town at a peak",
      "link": "https://www.boston.com/sports/boston-celtics/2026/05/08/jaylen-brown-comments-jayson-tatum/",
      "pubDate": "Fri, 08 May 2026 14:22:19 +0000",
      "description": "<p>Brown likes to be cryptic and casually candid, and then do the I-can\u2019t-believe-this-is-a-big-deal routine when something he says catches fire.</p>\n<p>The post <a href=\"https://www.boston.com/sports/boston-celtics/2026/05/08/jaylen-brown-comments-jayson-tatum/\">If this was Jaylen Brown\u2019s \u2018favorite\u2019 Celtics season, maybe it\u2019s time to let him leave town at a peak</a> appeared first on <a href=\"https://www.boston.com\">Boston.com</a>.</p>",
      "id": "12b6a09fba1057ea691626603b2c305b",
      "summary": [
        "Update: If this was Jaylen Brown\u2019s \u2018favorite\u2019 Celtics seas",
        "Details: <p>Brown likes to be cryptic and casually candid, ",
        "Visit Boston.com for complete coverage"
      ],
      "hookType": "NEWS_UPDATE"
    }
  ],
  "stats": {
    "totalProcessed": 5,
    "feedSize": 10,
    "timestamp": "2026-05-08T15:45:10.511772+00:00"
  }
}