{
  "lastUpdated": "2026-04-23T13:54:01.666200+00:00",
  "articles": [
    {
      "title": "This guy walked to Logan Airport from Cambridge. Here\u2019s how he did it.",
      "link": "https://www.boston.com/news/off-beat/2026/04/23/sam-westby-logan-airport-walk-from-cambridge/",
      "pubDate": "Thu, 23 Apr 2026 13:44:27 +0000",
      "description": "<p>Sam Westby took his social media followers along for the journey when he set out on foot for Logan last week. </p>\n<p>The post <a href=\"https://www.boston.com/news/off-beat/2026/04/23/sam-westby-logan-airport-walk-from-cambridge/\">This guy walked to Logan Airport from Cambridge. Here\u2019s how he did it.</a> appeared first on <a href=\"https://www.boston.com\">Boston.com</a>.</p>",
      "id": "33d9ee6e63993b4eb1a46b19140ac525",
      "summary": [
        "Update: This guy walked to Logan Airport from Cambridge. H",
        "Details: <p>Sam Westby took his social media followers alon",
        "Visit Boston.com for complete coverage"
      ],
      "hookType": "NEWS_UPDATE"
    },
    {
      "title": "5 best new restaurant openings and dining updates in Boston (April 23, 2026)",
      "link": "https://www.boston.com/food/restaurants/2026/04/23/restaurant-openings-april-23-2026/",
      "pubDate": "Thu, 23 Apr 2026 13:00:00 +0000",
      "description": "<p>Stay up-to-date on the best new restaurants, recent openings, and the biggest dining updates across Greater Boston's food scene.</p>\n<p>The post <a href=\"https://www.boston.com/food/restaurants/2026/04/23/restaurant-openings-april-23-2026/\">5 best new restaurant openings and dining updates in Boston (April 23, 2026)</a> appeared first on <a href=\"https://www.boston.com\">Boston.com</a>.</p>",
      "id": "b0e03e3635d7e44daf66b06b6eb7b5d8",
      "summary": [
        "Update: 5 best new restaurant openings and dining updates ",
        "Details: <p>Stay up-to-date on the best new restaurants, re",
        "Visit Boston.com for complete coverage"
      ],
      "hookType": "NEWS_UPDATE"
    },
    {
      "title": "What to expect this season at Acadia National Park",
      "link": "https://www.boston.com/travel/new-england-travel/2026/04/23/acadia-national-park/",
      "pubDate": "Thu, 23 Apr 2026 12:25:57 +0000",
      "description": "<p>The Island Explorer will offer spring service\u00a0to the park for the first time on May 20.   </p>\n<p>The post <a href=\"https://www.boston.com/travel/new-england-travel/2026/04/23/acadia-national-park/\">What to expect this season at Acadia National Park</a> appeared first on <a href=\"https://www.boston.com\">Boston.com</a>.</p>",
      "id": "24800a437e206f89a2c893078d32ea21",
      "summary": [
        "Update: What to expect this season at Acadia National Park",
        "Details: <p>The Island Explorer will offer spring service\u00a0t",
        "Visit Boston.com for complete coverage"
      ],
      "hookType": "NEWS_UPDATE"
    },
    {
      "title": "What is skillfishing? How employers can spot real skills in the AI hiring era.",
      "link": "https://www.boston.com/news/job-doc/2026/04/23/what-is-skillfishing/",
      "pubDate": "Thu, 23 Apr 2026 12:00:00 +0000",
      "description": "<p>AI tools are helping candidates look like perfect hires \u2014 even when they\u2019re not. </p>\n<p>The post <a href=\"https://www.boston.com/news/job-doc/2026/04/23/what-is-skillfishing/\">What is skillfishing? How employers can spot real skills in the AI hiring era.</a> appeared first on <a href=\"https://www.boston.com\">Boston.com</a>.</p>",
      "id": "c485231b0c52c730f047271e62b1ea3b",
      "summary": [
        "Update: What is skillfishing? How employers can spot real ",
        "Details: <p>AI tools are helping candidates look like perfe",
        "Visit Boston.com for complete coverage"
      ],
      "hookType": "NEWS_UPDATE"
    },
    {
      "title": "Mike Vrabel to seek counseling, will reportedly skip Day 3 of NFL Draft",
      "link": "https://www.boston.com/sports/new-england-patriots/2026/04/23/mike-vrabel-dianna-russini-nfl-draft-new-england-patriots-counseling/",
      "pubDate": "Thu, 23 Apr 2026 11:16:19 +0000",
      "description": "<p>\"This is not an easy thing for me to admit, but it is one that I know will make me a better person.\"</p>\n<p>The post <a href=\"https://www.boston.com/sports/new-england-patriots/2026/04/23/mike-vrabel-dianna-russini-nfl-draft-new-england-patriots-counseling/\">Mike Vrabel to seek counseling, will reportedly skip Day 3 of NFL Draft</a> appeared first on <a href=\"https://www.boston.com\">Boston.com</a>.</p>",
      "id": "c8d93169dad8557bc5d872aa6885df74",
      "summary": [
        "Update: Mike Vrabel to seek counseling, will reportedly sk",
        "Details: <p>\"This is not an easy thing for me to admit, but",
        "Visit Boston.com for complete coverage"
      ],
      "hookType": "NEWS_UPDATE"
    }
  ],
  "stats": {
    "totalProcessed": 5,
    "feedSize": 10,
    "timestamp": "2026-04-23T13:54:01.666219+00:00"
  }
}