{
  "lastUpdated": "2025-09-18T10:22:09.384845+00:00",
  "articles": [
    {
      "title": "5 can\u2019t-miss restaurant openings and dining updates in Boston this week",
      "link": "https://www.boston.com/food/food/2025/09/18/restaurant-openings-sept-18-2025/",
      "pubDate": "Thu, 18 Sep 2025 09:00:00 +0000",
      "description": "<p>Stay up to date on the best new restaurants, recent openings, and the biggest dining updates across Greater Boston's food scene.</p>\n<p>The post <a href=\"https://www.boston.com/food/food/2025/09/18/restaurant-openings-sept-18-2025/\">5 can\u2019t-miss restaurant openings and dining updates in Boston this week</a> appeared first on <a href=\"https://www.boston.com\">Boston.com</a>.</p>",
      "id": "456b584caa0e8e9a1e2ab11726709235",
      "summary": [
        "Update: 5 can\u2019t-miss restaurant openings and dining update",
        "Details: <p>Stay up to date on the best new restaurants, re",
        "Visit Boston.com for complete coverage"
      ],
      "hookType": "NEWS_UPDATE"
    }
  ],
  "stats": {
    "totalProcessed": 1,
    "feedSize": 10,
    "timestamp": "2025-09-18T10:22:09.384862+00:00"
  }
}